{"errors":[],"warnings":[],"namedChunkGroups":{"app":{"chunks":[5,0,2],"assets":["webpack-runtime-ac074376a6b1e65f9646.js","webpack-runtime-ac074376a6b1e65f9646.js.map","commons-721b3b012013ad5a1d68.js","commons-721b3b012013ad5a1d68.js.map","app-2c677af29bda2ac06323.js","app-2c677af29bda2ac06323.js.map"],"children":{},"childAssets":{}},"component---src-pages-404-js":{"chunks":[1,0,3],"assets":["styles.3dd4a4d1580fb868ce62.css","styles-ce0f6b799761d56e9e9b.js","styles-ce0f6b799761d56e9e9b.js.map","commons-721b3b012013ad5a1d68.js","commons-721b3b012013ad5a1d68.js.map","component---src-pages-404-js-72e1d304df32c3842c4e.js","component---src-pages-404-js-72e1d304df32c3842c4e.js.map"],"children":{},"childAssets":{}},"component---src-pages-index-js":{"chunks":[1,0,4],"assets":["styles.3dd4a4d1580fb868ce62.css","styles-ce0f6b799761d56e9e9b.js","styles-ce0f6b799761d56e9e9b.js.map","commons-721b3b012013ad5a1d68.js","commons-721b3b012013ad5a1d68.js.map","component---src-pages-index-js-755d3311bd101e8b38cd.js","component---src-pages-index-js-755d3311bd101e8b38cd.js.map"],"children":{},"childAssets":{}}},"assetsByChunkName":{"app":["webpack-runtime-ac074376a6b1e65f9646.js","commons-721b3b012013ad5a1d68.js","app-2c677af29bda2ac06323.js"],"component---src-pages-404-js":["styles.3dd4a4d1580fb868ce62.css","styles-ce0f6b799761d56e9e9b.js","commons-721b3b012013ad5a1d68.js","component---src-pages-404-js-72e1d304df32c3842c4e.js"],"component---src-pages-index-js":["styles.3dd4a4d1580fb868ce62.css","styles-ce0f6b799761d56e9e9b.js","commons-721b3b012013ad5a1d68.js","component---src-pages-index-js-755d3311bd101e8b38cd.js"]}}